deepflash2/__init__.py
deepflash2/_nbdev.py
deepflash2/all.py
deepflash2/config.py
deepflash2/data.py
deepflash2/gt.py
deepflash2/gui.py
deepflash2/inference.py
deepflash2/learner.py
deepflash2/losses.py
deepflash2/models.py
deepflash2/tta.py
deepflash2/utils.py
deepflash2-0.2.3.dist-info/LICENSE
deepflash2-0.2.3.dist-info/METADATA
deepflash2-0.2.3.dist-info/WHEEL
deepflash2-0.2.3.dist-info/top_level.txt
deepflash2-0.2.3.dist-info/RECORD
