Metadata-Version: 2.1
Name: deepflash2
Version: 0.2.3
Summary: A Deep learning pipeline for segmentation of fluorescent labels in microscopy images
Home-page: https://github.com/matjesg/deepflash2
Author: Matthias Griebel
Author-email: matthias.griebel@uni-wuerzburg.com
License: Apache Software License 2.0
Keywords: unet,deep learning,semantic segmentation,microscopy,fluorescent labels
Classifier: Development Status :: 3 - Alpha
Classifier: Intended Audience :: Developers
Classifier: License :: OSI Approved :: Apache Software License
Classifier: Natural Language :: English
Classifier: Programming Language :: Python :: 3.7
Classifier: Programming Language :: Python :: 3.8
Requires-Python: >=3.7
License-File: LICENSE
Requires-Dist: pip
Requires-Dist: packaging
Requires-Dist: fastai (>=2.1.7)
Requires-Dist: zarr (>=2.0)
Requires-Dist: tifffile (==2022.4.8)
Requires-Dist: scikit-image
Requires-Dist: imageio
Requires-Dist: ipywidgets
Requires-Dist: openpyxl
Requires-Dist: imagecodecs
Requires-Dist: albumentations (>=1.0.0)
Requires-Dist: natsort (>=7.1.1)
Requires-Dist: numba (>=0.52.0)
Requires-Dist: opencv-python-headless (<4.5.5,>=4.1.1)
Requires-Dist: timm (==0.6.7)
Requires-Dist: segmentation-models-pytorch-deepflash2
